citable_corpus/__init__.py
citable_corpus/corpus.py
citable_corpus/passage.py
citable_corpus-0.1.0.dist-info/METADATA
citable_corpus-0.1.0.dist-info/WHEEL
citable_corpus-0.1.0.dist-info/licenses/LICENSE
citable_corpus-0.1.0.dist-info/RECORD
