Metadata-Version: 2.4
Name: citable_corpus
Version: 0.1.0
Summary: A Python library for working with a corpus of texts canonically citable by CtsUrn.
License-File: LICENSE
Requires-Python: >=3.14
Requires-Dist: cite-exchange>=0.2.0
Requires-Dist: ipython
Requires-Dist: pydantic
Requires-Dist: urn-citation>=0.4.1
